README.md
README.rst
setup.py
packadd/__init__.py
packadd/__main__.py
packadd/command.py
packadd/config.py
packadd/packadd.py
packadd/tests.py
packadd/utils.py
vim_packadd.egg-info/PKG-INFO
vim_packadd.egg-info/SOURCES.txt
vim_packadd.egg-info/dependency_links.txt
vim_packadd.egg-info/entry_points.txt
vim_packadd.egg-info/requires.txt
vim_packadd.egg-info/top_level.txt