Metadata-Version: 2.1
Name: vim-packadd
Version: 0.6.3
Summary: Package manager for Vim8.
Home-page: https://github.com/antoinedray/vim-packadd
Author: Antoine Dray
Author-email: antoine.dray@epita.fr
Maintainer: Antoine Dray
Maintainer-email: antoine.dray@epita.fr
License: MIT
Platform: UNKNOWN
